ultrasphere/__init__.py
ultrasphere/__main__.py
ultrasphere/_coordinates.py
ultrasphere/_creation.py
ultrasphere/_draw.py
ultrasphere/_integral.py
ultrasphere/_random.py
ultrasphere/cli.py
ultrasphere/py.typed
ultrasphere/special/__init__.py
ultrasphere/special/_bessel.py
ultrasphere/special/_helmholtz.py
ultrasphere-2.0.2.dist-info/licenses/LICENSE
ultrasphere-2.0.2.dist-info/METADATA
ultrasphere-2.0.2.dist-info/WHEEL
ultrasphere-2.0.2.dist-info/entry_points.txt
ultrasphere-2.0.2.dist-info/top_level.txt
ultrasphere-2.0.2.dist-info/RECORD
