Metadata-Version: 2.4
Name: ultrasphere
Version: 2.0.2
Summary: Hyperspherical coordinates in NumPy / PyTorch / JAX.
Author-email: ultrasphere-dev <34j.95a2p@simplelogin.com>
License: MIT
Project-URL: Bug Tracker, https://github.com/ultrasphere-dev/ultrasphere/issues
Project-URL: Changelog, https://github.com/ultrasphere-dev/ultrasphere/blob/main/CHANGELOG.md
Project-URL: documentation, https://ultrasphere.readthedocs.io
Project-URL: repository, https://github.com/ultrasphere-dev/ultrasphere
Classifier: Development Status :: 2 - Pre-Alpha
Classifier: Intended Audience :: Developers
Classifier: Natural Language :: English
Classifier: Operating System :: OS Independent
Classifier: Programming Language :: Python :: 3.12
Classifier: Programming Language :: Python :: 3.13
Classifier: Topic :: Software Development :: Libraries
Requires-Python: >=3.12
License-File: LICENSE
Requires-Dist: aquarel>=0.0.7
Requires-Dist: array-api-compat>=1.12.0
Requires-Dist: array-api-extra>=0.8.0
Requires-Dist: jacobi-poly>=1.0.3
Requires-Dist: matplotlib>=3.10.3
Requires-Dist: networkx>=3.5
Requires-Dist: rich>=10
Requires-Dist: scipy>=1.15.3
Requires-Dist: strenum>=0.4.15
Requires-Dist: typer<1,>=0.15
Requires-Dist: types-array-api>=1.1.4
Provides-Extra: plot
Requires-Dist: pydot>=4.0.1; extra == "plot"
Requires-Dist: pygraphviz>=1.14; extra == "plot"
Dynamic: license-file
